knowledgehub/__init__.py
knowledgehub/api.py
knowledgehub/chemistryservice.py
knowledgehub/constants.py
knowledgehub/primitiveadapter.py
knowledgehub/semanticservice.py
knowledgehub/services.py
knowledgehub/similarityservice.py
knowledgehub-1.2.9.dist-info/LICENSE
knowledgehub-1.2.9.dist-info/METADATA
knowledgehub-1.2.9.dist-info/WHEEL
knowledgehub-1.2.9.dist-info/top_level.txt
knowledgehub-1.2.9.dist-info/RECORD
